<?xml version='1.0' encoding='UTF-8'?>
<Container>
    <MessageHeader>
        <MessageStatusCode>UPDATED</MessageStatusCode>
        <MessageCreationDateTime>2026-05-12T18:57:17</MessageCreationDateTime>
        <MessageSchemaVersion>1.6</MessageSchemaVersion>
        <MessageUniqueID>938</MessageUniqueID>
        <MessageSendingOrganization>
            <FacilityName>Lagos State Mainland Hospital</FacilityName>
            <FacilityID>kzjkCk8UnGR</FacilityID>
            <FacilityTypeCode>FAC</FacilityTypeCode>
        </MessageSendingOrganization>
    </MessageHeader>
    <IndividualReport>
        <PatientDemographics>
            <PatientIdentifier>kzjkCk8UnGR_0f6ce1f3-f877-4867-9c1c-1e278d36dc2f</PatientIdentifier>
            <TreatmentFacility>
                <FacilityName>Lagos State Mainland Hospital</FacilityName>
                <FacilityID>kzjkCk8UnGR</FacilityID>
                <FacilityTypeCode>FAC</FacilityTypeCode>
            </TreatmentFacility>
            <PatientDateOfBirth>1972-11-28</PatientDateOfBirth>
            <PatientSexCode>F</PatientSexCode>
            <StateOfNigeriaOriginCode>25</StateOfNigeriaOriginCode>
        </PatientDemographics>
        <Condition>
            <ConditionCode>86406008</ConditionCode>
            <ProgramArea>
                <ProgramAreaCode>HIV</ProgramAreaCode>
            </ProgramArea>
            <Regimen>
                <VisitID>259eb5ca-87fc-4231-b905-c21a3a3f2c01</VisitID>
                <VisitDate>2026-04-10</VisitDate>
                <PrescribedRegimen>
                    <Code>1c</Code>
                    <CodeDescTxt>ABC-3TC-DTG</CodeDescTxt>
                </PrescribedRegimen>
                <PrescribedRegimenTypeCode>ART</PrescribedRegimenTypeCode>
                <PrescribedRegimenDuration>90</PrescribedRegimenDuration>
                <PrescribedRegimenDispensedDate>2026-04-10</PrescribedRegimenDispensedDate>
                <DateRegimenStarted>2024-08-08</DateRegimenStarted>
                <MultiMonthDispensing>MMD3</MultiMonthDispensing>
            </Regimen>
        </Condition>
    </IndividualReport>
</Container>