<?xml version='1.0' encoding='UTF-8'?>
<Container>
    <MessageHeader>
        <MessageStatusCode>UPDATED</MessageStatusCode>
        <MessageCreationDateTime>2026-05-12T18:57:17</MessageCreationDateTime>
        <MessageSchemaVersion>1.6</MessageSchemaVersion>
        <MessageUniqueID>891</MessageUniqueID>
        <MessageSendingOrganization>
            <FacilityName>Lagos General Hospital</FacilityName>
            <FacilityID>zyxDXEYBxqA</FacilityID>
            <FacilityTypeCode>FAC</FacilityTypeCode>
        </MessageSendingOrganization>
    </MessageHeader>
    <IndividualReport>
        <PatientDemographics>
            <PatientIdentifier>zyxDXEYBxqA_1e050272-6ef9-450f-8586-a7b2ea5cc506</PatientIdentifier>
            <TreatmentFacility>
                <FacilityName>Lagos General Hospital</FacilityName>
                <FacilityID>zyxDXEYBxqA</FacilityID>
                <FacilityTypeCode>FAC</FacilityTypeCode>
            </TreatmentFacility>
            <PatientDateOfBirth>1977-09-09</PatientDateOfBirth>
            <PatientSexCode>F</PatientSexCode>
            <StateOfNigeriaOriginCode>25</StateOfNigeriaOriginCode>
        </PatientDemographics>
        <Condition>
            <ConditionCode>86406008</ConditionCode>
            <ProgramArea>
                <ProgramAreaCode>HIV</ProgramAreaCode>
            </ProgramArea>
            <Regimen>
                <VisitID>88a06b70-339b-4c17-9ccb-d54bfdcc7ff4</VisitID>
                <VisitDate>2026-04-28</VisitDate>
                <PrescribedRegimen>
                    <Code>5b</Code>
                    <CodeDescTxt>AZT-3TC-ATV/r</CodeDescTxt>
                </PrescribedRegimen>
                <PrescribedRegimenTypeCode>ART</PrescribedRegimenTypeCode>
                <PrescribedRegimenDuration>180</PrescribedRegimenDuration>
                <PrescribedRegimenDispensedDate>2026-04-28</PrescribedRegimenDispensedDate>
                <DateRegimenStarted>2022-03-09</DateRegimenStarted>
                <MultiMonthDispensing>MMD2</MultiMonthDispensing>
            </Regimen>
        </Condition>
    </IndividualReport>
</Container>